{
  "date": "2025-12-04",
  "projects": {
    "nxtqube_webapp": {
      "totalLinesAdded": 386,
      "totalLinesRemoved": 0,
      "totalActiveTime": 0,
      "files": {
        "/Users/sakshi/Desktop/nxtqube/Argos/nxtqube_webapp/frontend/src/components/Mission/createMission/WaypointAction.jsx": [
          {
            "timestamp": "2025-12-04T08:15:21.758Z",
            "fileName": "/Users/sakshi/Desktop/nxtqube/Argos/nxtqube_webapp/frontend/src/components/Mission/createMission/WaypointAction.jsx",
            "fileType": ".jsx",
            "linesAdded": 386,
            "linesRemoved": 0,
            "projectName": "nxtqube_webapp",
            "content": {
              "added": [],
              "removed": []
            },
            "duration": 0,
            "language": "jsx"
          }
        ]
      },
      "languageStats": {
        "jsx": 0
      },
      "changeFrequency": {
        "13": 0
      },
      "topFiles": [
        "/Users/sakshi/Desktop/nxtqube/Argos/nxtqube_webapp/frontend/src/components/Mission/createMission/WaypointAction.jsx"
      ],
      "averageChangeSize": 386
    }
  },
  "totalActiveTime": 0,
  "totalProjects": 1,
  "totalFiles": 1,
  "mostActiveHours": [
    13
  ],
  "mostUsedLanguages": [
    "jsx"
  ]
}