{
  "date": "2026-01-13",
  "projects": {
    "nxtqube_webapp": {
      "totalLinesAdded": 3161,
      "totalLinesRemoved": 57,
      "totalActiveTime": 21,
      "files": {
        "/Users/sakshi/Desktop/nxtqube/Argos/nxtqube_webapp/frontend/src/components/Mission/ExistingMission/ExistingMission.jsx": [
          {
            "timestamp": "2026-01-13T05:59:50.715Z",
            "fileName": "/Users/sakshi/Desktop/nxtqube/Argos/nxtqube_webapp/frontend/src/components/Mission/ExistingMission/ExistingMission.jsx",
            "fileType": ".jsx",
            "linesAdded": 683,
            "linesRemoved": 0,
            "projectName": "nxtqube_webapp",
            "content": {
              "added": [],
              "removed": []
            },
            "duration": 0,
            "language": "jsx"
          },
          {
            "timestamp": "2026-01-13T06:00:02.494Z",
            "fileName": "/Users/sakshi/Desktop/nxtqube/Argos/nxtqube_webapp/frontend/src/components/Mission/ExistingMission/ExistingMission.jsx",
            "fileType": ".jsx",
            "linesAdded": 0,
            "linesRemoved": 9,
            "projectName": "nxtqube_webapp",
            "content": {
              "added": [],
              "removed": []
            },
            "duration": 1,
            "language": "jsx"
          },
          {
            "timestamp": "2026-01-13T06:00:33.476Z",
            "fileName": "/Users/sakshi/Desktop/nxtqube/Argos/nxtqube_webapp/frontend/src/components/Mission/ExistingMission/ExistingMission.jsx",
            "fileType": ".jsx",
            "linesAdded": 0,
            "linesRemoved": 2,
            "projectName": "nxtqube_webapp",
            "content": {
              "added": [],
              "removed": []
            },
            "duration": 1,
            "language": "jsx"
          },
          {
            "timestamp": "2026-01-13T06:04:04.886Z",
            "fileName": "/Users/sakshi/Desktop/nxtqube/Argos/nxtqube_webapp/frontend/src/components/Mission/ExistingMission/ExistingMission.jsx",
            "fileType": ".jsx",
            "linesAdded": 0,
            "linesRemoved": 2,
            "projectName": "nxtqube_webapp",
            "content": {
              "added": [],
              "removed": []
            },
            "duration": 4,
            "language": "jsx"
          },
          {
            "timestamp": "2026-01-13T06:04:09.951Z",
            "fileName": "/Users/sakshi/Desktop/nxtqube/Argos/nxtqube_webapp/frontend/src/components/Mission/ExistingMission/ExistingMission.jsx",
            "fileType": ".jsx",
            "linesAdded": 0,
            "linesRemoved": 4,
            "projectName": "nxtqube_webapp",
            "content": {
              "added": [],
              "removed": []
            },
            "duration": 1,
            "language": "jsx"
          },
          {
            "timestamp": "2026-01-13T10:08:12.648Z",
            "fileName": "/Users/sakshi/Desktop/nxtqube/Argos/nxtqube_webapp/frontend/src/components/Mission/ExistingMission/ExistingMission.jsx",
            "fileType": ".jsx",
            "linesAdded": 15,
            "linesRemoved": 0,
            "projectName": "nxtqube_webapp",
            "content": {
              "added": [],
              "removed": []
            },
            "duration": 3,
            "language": "jsx"
          },
          {
            "timestamp": "2026-01-13T10:08:13.662Z",
            "fileName": "/Users/sakshi/Desktop/nxtqube/Argos/nxtqube_webapp/frontend/src/components/Mission/ExistingMission/ExistingMission.jsx",
            "fileType": ".jsx",
            "linesAdded": 0,
            "linesRemoved": 25,
            "projectName": "nxtqube_webapp",
            "content": {
              "added": [],
              "removed": []
            },
            "duration": 1,
            "language": "jsx"
          },
          {
            "timestamp": "2026-01-13T10:08:59.546Z",
            "fileName": "/Users/sakshi/Desktop/nxtqube/Argos/nxtqube_webapp/frontend/src/components/Mission/ExistingMission/ExistingMission.jsx",
            "fileType": ".jsx",
            "linesAdded": 0,
            "linesRemoved": 3,
            "projectName": "nxtqube_webapp",
            "content": {
              "added": [],
              "removed": []
            },
            "duration": 1,
            "language": "jsx"
          },
          {
            "timestamp": "2026-01-13T10:09:09.513Z",
            "fileName": "/Users/sakshi/Desktop/nxtqube/Argos/nxtqube_webapp/frontend/src/components/Mission/ExistingMission/ExistingMission.jsx",
            "fileType": ".jsx",
            "linesAdded": 0,
            "linesRemoved": 1,
            "projectName": "nxtqube_webapp",
            "content": {
              "added": [],
              "removed": []
            },
            "duration": 1,
            "language": "jsx"
          },
          {
            "timestamp": "2026-01-13T10:10:17.881Z",
            "fileName": "/Users/sakshi/Desktop/nxtqube/Argos/nxtqube_webapp/frontend/src/components/Mission/ExistingMission/ExistingMission.jsx",
            "fileType": ".jsx",
            "linesAdded": 0,
            "linesRemoved": 7,
            "projectName": "nxtqube_webapp",
            "content": {
              "added": [],
              "removed": []
            },
            "duration": 2,
            "language": "jsx"
          }
        ],
        "/Users/sakshi/Desktop/nxtqube/Argos/nxtqube_webapp/frontend/src/components/Mission/createMission/DeleteMission.jsx": [
          {
            "timestamp": "2026-01-13T06:13:03.139Z",
            "fileName": "/Users/sakshi/Desktop/nxtqube/Argos/nxtqube_webapp/frontend/src/components/Mission/createMission/DeleteMission.jsx",
            "fileType": ".jsx",
            "linesAdded": 38,
            "linesRemoved": 0,
            "projectName": "nxtqube_webapp",
            "content": {
              "added": [],
              "removed": []
            },
            "duration": 0,
            "language": "jsx"
          }
        ],
        "/Users/sakshi/Desktop/nxtqube/Argos/nxtqube_webapp/frontend/src/components/Mission/createMission/createGridMission.jsx": [
          {
            "timestamp": "2026-01-13T06:15:30.401Z",
            "fileName": "/Users/sakshi/Desktop/nxtqube/Argos/nxtqube_webapp/frontend/src/components/Mission/createMission/createGridMission.jsx",
            "fileType": ".jsx",
            "linesAdded": 2423,
            "linesRemoved": 0,
            "projectName": "nxtqube_webapp",
            "content": {
              "added": [],
              "removed": []
            },
            "duration": 3,
            "language": "jsx"
          },
          {
            "timestamp": "2026-01-13T06:22:32.329Z",
            "fileName": "/Users/sakshi/Desktop/nxtqube/Argos/nxtqube_webapp/frontend/src/components/Mission/createMission/createGridMission.jsx",
            "fileType": ".jsx",
            "linesAdded": 0,
            "linesRemoved": 1,
            "projectName": "nxtqube_webapp",
            "content": {
              "added": [],
              "removed": []
            },
            "duration": 0,
            "language": "jsx"
          },
          {
            "timestamp": "2026-01-13T06:23:08.858Z",
            "fileName": "/Users/sakshi/Desktop/nxtqube/Argos/nxtqube_webapp/frontend/src/components/Mission/createMission/createGridMission.jsx",
            "fileType": ".jsx",
            "linesAdded": 0,
            "linesRemoved": 1,
            "projectName": "nxtqube_webapp",
            "content": {
              "added": [],
              "removed": []
            },
            "duration": 1,
            "language": "jsx"
          },
          {
            "timestamp": "2026-01-13T07:45:23.126Z",
            "fileName": "/Users/sakshi/Desktop/nxtqube/Argos/nxtqube_webapp/frontend/src/components/Mission/createMission/createGridMission.jsx",
            "fileType": ".jsx",
            "linesAdded": 1,
            "linesRemoved": 0,
            "projectName": "nxtqube_webapp",
            "content": {
              "added": [],
              "removed": []
            },
            "duration": 0,
            "language": "jsx"
          },
          {
            "timestamp": "2026-01-13T09:16:53.873Z",
            "fileName": "/Users/sakshi/Desktop/nxtqube/Argos/nxtqube_webapp/frontend/src/components/Mission/createMission/createGridMission.jsx",
            "fileType": ".jsx",
            "linesAdded": 0,
            "linesRemoved": 1,
            "projectName": "nxtqube_webapp",
            "content": {
              "added": [],
              "removed": []
            },
            "duration": 0,
            "language": "jsx"
          },
          {
            "timestamp": "2026-01-13T10:03:57.295Z",
            "fileName": "/Users/sakshi/Desktop/nxtqube/Argos/nxtqube_webapp/frontend/src/components/Mission/createMission/createGridMission.jsx",
            "fileType": ".jsx",
            "linesAdded": 1,
            "linesRemoved": 0,
            "projectName": "nxtqube_webapp",
            "content": {
              "added": [],
              "removed": []
            },
            "duration": 0,
            "language": "jsx"
          },
          {
            "timestamp": "2026-01-13T10:05:49.788Z",
            "fileName": "/Users/sakshi/Desktop/nxtqube/Argos/nxtqube_webapp/frontend/src/components/Mission/createMission/createGridMission.jsx",
            "fileType": ".jsx",
            "linesAdded": 0,
            "linesRemoved": 1,
            "projectName": "nxtqube_webapp",
            "content": {
              "added": [],
              "removed": []
            },
            "duration": 2,
            "language": "jsx"
          }
        ]
      },
      "languageStats": {
        "jsx": 2
      },
      "changeFrequency": {
        "11": 2
      },
      "topFiles": [
        "/Users/sakshi/Desktop/nxtqube/Argos/nxtqube_webapp/frontend/src/components/Mission/ExistingMission/ExistingMission.jsx"
      ],
      "averageChangeSize": 231.33333333333334
    }
  },
  "totalActiveTime": 2,
  "totalProjects": 1,
  "totalFiles": 1,
  "mostActiveHours": [
    11
  ],
  "mostUsedLanguages": [
    "jsx"
  ]
}