{
  "date": "2026-03-26",
  "projects": {
    "nxtqube_webapp": {
      "totalLinesAdded": 1397,
      "totalLinesRemoved": 26,
      "totalActiveTime": 18,
      "files": {
        "/Users/sakshi/Desktop/nxtqube/Argos/nxtqube_webapp/frontend/src/components/Mission/createMission/components/3dMission/stack/draw.stack.boundry.ts": [
          {
            "timestamp": "2026-03-26T08:10:21.700Z",
            "fileName": "/Users/sakshi/Desktop/nxtqube/Argos/nxtqube_webapp/frontend/src/components/Mission/createMission/components/3dMission/stack/draw.stack.boundry.ts",
            "fileType": ".ts",
            "linesAdded": 146,
            "linesRemoved": 0,
            "projectName": "nxtqube_webapp",
            "content": {
              "added": [],
              "removed": []
            },
            "duration": 0,
            "language": "ts"
          },
          {
            "timestamp": "2026-03-26T08:10:22.742Z",
            "fileName": "/Users/sakshi/Desktop/nxtqube/Argos/nxtqube_webapp/frontend/src/components/Mission/createMission/components/3dMission/stack/draw.stack.boundry.ts",
            "fileType": ".ts",
            "linesAdded": 0,
            "linesRemoved": 1,
            "projectName": "nxtqube_webapp",
            "content": {
              "added": [],
              "removed": []
            },
            "duration": 1,
            "language": "ts"
          },
          {
            "timestamp": "2026-03-26T12:02:16.031Z",
            "fileName": "/Users/sakshi/Desktop/nxtqube/Argos/nxtqube_webapp/frontend/src/components/Mission/createMission/components/3dMission/stack/draw.stack.boundry.ts",
            "fileType": ".ts",
            "linesAdded": 0,
            "linesRemoved": 13,
            "projectName": "nxtqube_webapp",
            "content": {
              "added": [],
              "removed": []
            },
            "duration": 4,
            "language": "ts"
          },
          {
            "timestamp": "2026-03-26T12:02:17.069Z",
            "fileName": "/Users/sakshi/Desktop/nxtqube/Argos/nxtqube_webapp/frontend/src/components/Mission/createMission/components/3dMission/stack/draw.stack.boundry.ts",
            "fileType": ".ts",
            "linesAdded": 13,
            "linesRemoved": 0,
            "projectName": "nxtqube_webapp",
            "content": {
              "added": [],
              "removed": []
            },
            "duration": 1,
            "language": "ts"
          },
          {
            "timestamp": "2026-03-26T12:02:21.889Z",
            "fileName": "/Users/sakshi/Desktop/nxtqube/Argos/nxtqube_webapp/frontend/src/components/Mission/createMission/components/3dMission/stack/draw.stack.boundry.ts",
            "fileType": ".ts",
            "linesAdded": 16,
            "linesRemoved": 0,
            "projectName": "nxtqube_webapp",
            "content": {
              "added": [],
              "removed": []
            },
            "duration": 1,
            "language": "ts"
          },
          {
            "timestamp": "2026-03-26T12:02:58.187Z",
            "fileName": "/Users/sakshi/Desktop/nxtqube/Argos/nxtqube_webapp/frontend/src/components/Mission/createMission/components/3dMission/stack/draw.stack.boundry.ts",
            "fileType": ".ts",
            "linesAdded": 6,
            "linesRemoved": 0,
            "projectName": "nxtqube_webapp",
            "content": {
              "added": [],
              "removed": []
            },
            "duration": 1,
            "language": "ts"
          }
        ],
        "/Users/sakshi/Desktop/nxtqube/Argos/nxtqube_webapp/frontend/src/components/Mission/createMission/components/3dMission/stack/StackMissionControl.tsx": [
          {
            "timestamp": "2026-03-26T10:37:09.307Z",
            "fileName": "/Users/sakshi/Desktop/nxtqube/Argos/nxtqube_webapp/frontend/src/components/Mission/createMission/components/3dMission/stack/StackMissionControl.tsx",
            "fileType": ".tsx",
            "linesAdded": 683,
            "linesRemoved": 0,
            "projectName": "nxtqube_webapp",
            "content": {
              "added": [],
              "removed": []
            },
            "duration": 0,
            "language": "tsx"
          },
          {
            "timestamp": "2026-03-26T10:37:12.713Z",
            "fileName": "/Users/sakshi/Desktop/nxtqube/Argos/nxtqube_webapp/frontend/src/components/Mission/createMission/components/3dMission/stack/StackMissionControl.tsx",
            "fileType": ".tsx",
            "linesAdded": 8,
            "linesRemoved": 0,
            "projectName": "nxtqube_webapp",
            "content": {
              "added": [],
              "removed": []
            },
            "duration": 1,
            "language": "tsx"
          },
          {
            "timestamp": "2026-03-26T10:37:16.924Z",
            "fileName": "/Users/sakshi/Desktop/nxtqube/Argos/nxtqube_webapp/frontend/src/components/Mission/createMission/components/3dMission/stack/StackMissionControl.tsx",
            "fileType": ".tsx",
            "linesAdded": 2,
            "linesRemoved": 0,
            "projectName": "nxtqube_webapp",
            "content": {
              "added": [],
              "removed": []
            },
            "duration": 1,
            "language": "tsx"
          },
          {
            "timestamp": "2026-03-26T10:37:36.540Z",
            "fileName": "/Users/sakshi/Desktop/nxtqube/Argos/nxtqube_webapp/frontend/src/components/Mission/createMission/components/3dMission/stack/StackMissionControl.tsx",
            "fileType": ".tsx",
            "linesAdded": 0,
            "linesRemoved": 2,
            "projectName": "nxtqube_webapp",
            "content": {
              "added": [],
              "removed": []
            },
            "duration": 1,
            "language": "tsx"
          },
          {
            "timestamp": "2026-03-26T10:37:40.606Z",
            "fileName": "/Users/sakshi/Desktop/nxtqube/Argos/nxtqube_webapp/frontend/src/components/Mission/createMission/components/3dMission/stack/StackMissionControl.tsx",
            "fileType": ".tsx",
            "linesAdded": 2,
            "linesRemoved": 0,
            "projectName": "nxtqube_webapp",
            "content": {
              "added": [],
              "removed": []
            },
            "duration": 1,
            "language": "tsx"
          },
          {
            "timestamp": "2026-03-26T11:02:26.661Z",
            "fileName": "/Users/sakshi/Desktop/nxtqube/Argos/nxtqube_webapp/frontend/src/components/Mission/createMission/components/3dMission/stack/StackMissionControl.tsx",
            "fileType": ".tsx",
            "linesAdded": 0,
            "linesRemoved": 10,
            "projectName": "nxtqube_webapp",
            "content": {
              "added": [],
              "removed": []
            },
            "duration": 0,
            "language": "tsx"
          },
          {
            "timestamp": "2026-03-26T11:59:06.190Z",
            "fileName": "/Users/sakshi/Desktop/nxtqube/Argos/nxtqube_webapp/frontend/src/components/Mission/createMission/components/3dMission/stack/StackMissionControl.tsx",
            "fileType": ".tsx",
            "linesAdded": 3,
            "linesRemoved": 0,
            "projectName": "nxtqube_webapp",
            "content": {
              "added": [],
              "removed": []
            },
            "duration": 0,
            "language": "tsx"
          }
        ],
        "/Users/sakshi/Desktop/nxtqube/Argos/nxtqube_webapp/frontend/src/components/Mission/createMission/components/3dMission/stack/StackMission3D.tsx": [
          {
            "timestamp": "2026-03-26T12:05:10.152Z",
            "fileName": "/Users/sakshi/Desktop/nxtqube/Argos/nxtqube_webapp/frontend/src/components/Mission/createMission/components/3dMission/stack/StackMission3D.tsx",
            "fileType": ".tsx",
            "linesAdded": 512,
            "linesRemoved": 0,
            "projectName": "nxtqube_webapp",
            "content": {
              "added": [],
              "removed": []
            },
            "duration": 3,
            "language": "tsx"
          },
          {
            "timestamp": "2026-03-26T12:05:11.235Z",
            "fileName": "/Users/sakshi/Desktop/nxtqube/Argos/nxtqube_webapp/frontend/src/components/Mission/createMission/components/3dMission/stack/StackMission3D.tsx",
            "fileType": ".tsx",
            "linesAdded": 1,
            "linesRemoved": 0,
            "projectName": "nxtqube_webapp",
            "content": {
              "added": [],
              "removed": []
            },
            "duration": 1,
            "language": "tsx"
          },
          {
            "timestamp": "2026-03-26T12:05:21.720Z",
            "fileName": "/Users/sakshi/Desktop/nxtqube/Argos/nxtqube_webapp/frontend/src/components/Mission/createMission/components/3dMission/stack/StackMission3D.tsx",
            "fileType": ".tsx",
            "linesAdded": 1,
            "linesRemoved": 0,
            "projectName": "nxtqube_webapp",
            "content": {
              "added": [],
              "removed": []
            },
            "duration": 1,
            "language": "tsx"
          },
          {
            "timestamp": "2026-03-26T12:05:25.800Z",
            "fileName": "/Users/sakshi/Desktop/nxtqube/Argos/nxtqube_webapp/frontend/src/components/Mission/createMission/components/3dMission/stack/StackMission3D.tsx",
            "fileType": ".tsx",
            "linesAdded": 4,
            "linesRemoved": 0,
            "projectName": "nxtqube_webapp",
            "content": {
              "added": [],
              "removed": []
            },
            "duration": 1,
            "language": "tsx"
          }
        ]
      },
      "languageStats": {
        "ts": 1
      },
      "changeFrequency": {
        "13": 1
      },
      "topFiles": [
        "/Users/sakshi/Desktop/nxtqube/Argos/nxtqube_webapp/frontend/src/components/Mission/createMission/components/3dMission/stack/draw.stack.boundry.ts"
      ],
      "averageChangeSize": 73.5
    }
  },
  "totalActiveTime": 1,
  "totalProjects": 1,
  "totalFiles": 1,
  "mostActiveHours": [
    13
  ],
  "mostUsedLanguages": [
    "ts"
  ]
}