{
  "date": "2025-10-14",
  "projects": {
    "nxtqube_webapp": {
      "totalLinesAdded": 851,
      "totalLinesRemoved": 1,
      "totalActiveTime": 1,
      "files": {
        "/Users/sakshi/Desktop/nxtqube/Argos/nxtqube_webapp/frontend/src/components/Mission/createMission/create3DMission.jsx": [
          {
            "timestamp": "2025-10-14T05:32:05.031Z",
            "fileName": "/Users/sakshi/Desktop/nxtqube/Argos/nxtqube_webapp/frontend/src/components/Mission/createMission/create3DMission.jsx",
            "fileType": ".jsx",
            "linesAdded": 851,
            "linesRemoved": 0,
            "projectName": "nxtqube_webapp",
            "content": {
              "added": [],
              "removed": []
            },
            "duration": 0,
            "language": "jsx"
          },
          {
            "timestamp": "2025-10-14T05:32:06.053Z",
            "fileName": "/Users/sakshi/Desktop/nxtqube/Argos/nxtqube_webapp/frontend/src/components/Mission/createMission/create3DMission.jsx",
            "fileType": ".jsx",
            "linesAdded": 0,
            "linesRemoved": 1,
            "projectName": "nxtqube_webapp",
            "content": {
              "added": [],
              "removed": []
            },
            "duration": 1,
            "language": "jsx"
          }
        ]
      },
      "languageStats": {
        "jsx": 1
      },
      "changeFrequency": {
        "11": 1
      },
      "topFiles": [
        "/Users/sakshi/Desktop/nxtqube/Argos/nxtqube_webapp/frontend/src/components/Mission/createMission/create3DMission.jsx"
      ],
      "averageChangeSize": 426
    }
  },
  "totalActiveTime": 1,
  "totalProjects": 1,
  "totalFiles": 1,
  "mostActiveHours": [
    11
  ],
  "mostUsedLanguages": [
    "jsx"
  ]
}